<?xml version="1.0" encoding="UTF-8" standalone="no"?><report><package name="org/apache/commons/math3/geometry/spherical/oned">
        <class name="org/apache/commons/math3/geometry/spherical/oned/SubLimitAngle" sourcefilename="SubLimitAngle.java">
            <method desc="(Lorg/apache/commons/math3/geometry/partitioning/Hyperplane;Lorg/apache/commons/math3/geometry/partitioning/Region;)V" line="35" name="&lt;init&gt;">
                <counter covered="0" missed="5" type="INSTRUCTION"/>
                <counter covered="0" missed="2" type="LINE"/>
                <counter covered="0" missed="1" type="COMPLEXITY"/>
                <counter covered="0" missed="1" type="METHOD"/>
            </method>
            <method desc="()D" line="41" name="getSize">
                <counter covered="0" missed="2" type="INSTRUCTION"/>
                <counter covered="0" missed="1" type="LINE"/>
                <counter covered="0" missed="1" type="COMPLEXITY"/>
                <counter covered="0" missed="1" type="METHOD"/>
            </method>
            <method desc="()Z" line="47" name="isEmpty">
                <counter covered="0" missed="2" type="INSTRUCTION"/>
                <counter covered="0" missed="1" type="LINE"/>
                <counter covered="0" missed="1" type="COMPLEXITY"/>
                <counter covered="0" missed="1" type="METHOD"/>
            </method>
            <method desc="(Lorg/apache/commons/math3/geometry/partitioning/Hyperplane;Lorg/apache/commons/math3/geometry/partitioning/Region;)Lorg/apache/commons/math3/geometry/partitioning/AbstractSubHyperplane;" line="54" name="buildNew">
                <counter covered="0" missed="6" type="INSTRUCTION"/>
                <counter covered="0" missed="1" type="LINE"/>
                <counter covered="0" missed="1" type="COMPLEXITY"/>
                <counter covered="0" missed="1" type="METHOD"/>
            </method>
            <method desc="(Lorg/apache/commons/math3/geometry/partitioning/Hyperplane;)Lorg/apache/commons/math3/geometry/partitioning/SubHyperplane$SplitSubHyperplane;" line="60" name="split">
                <counter covered="0" missed="23" type="INSTRUCTION"/>
                <counter covered="0" missed="2" type="BRANCH"/>
                <counter covered="0" missed="2" type="LINE"/>
                <counter covered="0" missed="2" type="COMPLEXITY"/>
                <counter covered="0" missed="1" type="METHOD"/>
            </method>
            <counter covered="0" missed="38" type="INSTRUCTION"/>
            <counter covered="0" missed="2" type="BRANCH"/>
            <counter covered="0" missed="7" type="LINE"/>
            <counter covered="0" missed="6" type="COMPLEXITY"/>
            <counter covered="0" missed="5" type="METHOD"/>
            <counter covered="0" missed="1" type="CLASS"/>
        </class>
        <class name="org/apache/commons/math3/geometry/spherical/oned/S1Point" sourcefilename="S1Point.java">
            <method desc="(D)V" line="51" name="&lt;init&gt;">
                <counter covered="0" missed="13" type="INSTRUCTION"/>
                <counter covered="0" missed="2" type="LINE"/>
                <counter covered="0" missed="1" type="COMPLEXITY"/>
                <counter covered="0" missed="1" type="METHOD"/>
            </method>
            <method desc="(DLorg/apache/commons/math3/geometry/euclidean/twod/Vector2D;)V" line="59" name="&lt;init&gt;">
                <counter covered="0" missed="9" type="INSTRUCTION"/>
                <counter covered="0" missed="4" type="LINE"/>
                <counter covered="0" missed="1" type="COMPLEXITY"/>
                <counter covered="0" missed="1" type="METHOD"/>
            </method>
            <method desc="()D" line="69" name="getAlpha">
                <counter covered="0" missed="3" type="INSTRUCTION"/>
                <counter covered="0" missed="1" type="LINE"/>
                <counter covered="0" missed="1" type="COMPLEXITY"/>
                <counter covered="0" missed="1" type="METHOD"/>
            </method>
            <method desc="()Lorg/apache/commons/math3/geometry/euclidean/twod/Vector2D;" line="76" name="getVector">
                <counter covered="0" missed="3" type="INSTRUCTION"/>
                <counter covered="0" missed="1" type="LINE"/>
                <counter covered="0" missed="1" type="COMPLEXITY"/>
                <counter covered="0" missed="1" type="METHOD"/>
            </method>
            <method desc="()Lorg/apache/commons/math3/geometry/Space;" line="81" name="getSpace">
                <counter covered="0" missed="2" type="INSTRUCTION"/>
                <counter covered="0" missed="1" type="LINE"/>
                <counter covered="0" missed="1" type="COMPLEXITY"/>
                <counter covered="0" missed="1" type="METHOD"/>
            </method>
            <method desc="()Z" line="86" name="isNaN">
                <counter covered="0" missed="4" type="INSTRUCTION"/>
                <counter covered="0" missed="1" type="LINE"/>
                <counter covered="0" missed="1" type="COMPLEXITY"/>
                <counter covered="0" missed="1" type="METHOD"/>
            </method>
            <method desc="(Lorg/apache/commons/math3/geometry/Point;)D" line="91" name="distance">
                <counter covered="0" missed="5" type="INSTRUCTION"/>
                <counter covered="0" missed="1" type="LINE"/>
                <counter covered="0" missed="1" type="COMPLEXITY"/>
                <counter covered="0" missed="1" type="METHOD"/>
            </method>
            <method desc="(Lorg/apache/commons/math3/geometry/spherical/oned/S1Point;Lorg/apache/commons/math3/geometry/spherical/oned/S1Point;)D" line="100" name="distance">
                <counter covered="0" missed="6" type="INSTRUCTION"/>
                <counter covered="0" missed="1" type="LINE"/>
                <counter covered="0" missed="1" type="COMPLEXITY"/>
                <counter covered="0" missed="1" type="METHOD"/>
            </method>
            <method desc="(Ljava/lang/Object;)Z" line="125" name="equals">
                <counter covered="0" missed="29" type="INSTRUCTION"/>
                <counter covered="0" missed="8" type="BRANCH"/>
                <counter covered="0" missed="8" type="LINE"/>
                <counter covered="0" missed="5" type="COMPLEXITY"/>
                <counter covered="0" missed="1" type="METHOD"/>
            </method>
            <method desc="()I" line="151" name="hashCode">
                <counter covered="0" missed="11" type="INSTRUCTION"/>
                <counter covered="0" missed="2" type="BRANCH"/>
                <counter covered="0" missed="3" type="LINE"/>
                <counter covered="0" missed="2" type="COMPLEXITY"/>
                <counter covered="0" missed="1" type="METHOD"/>
            </method>
            <method desc="()V" line="33" name="&lt;clinit&gt;">
                <counter covered="0" missed="7" type="INSTRUCTION"/>
                <counter covered="0" missed="1" type="LINE"/>
                <counter covered="0" missed="1" type="COMPLEXITY"/>
                <counter covered="0" missed="1" type="METHOD"/>
            </method>
            <counter covered="0" missed="92" type="INSTRUCTION"/>
            <counter covered="0" missed="10" type="BRANCH"/>
            <counter covered="0" missed="24" type="LINE"/>
            <counter covered="0" missed="16" type="COMPLEXITY"/>
            <counter covered="0" missed="11" type="METHOD"/>
            <counter covered="0" missed="1" type="CLASS"/>
        </class>
        <class name="org/apache/commons/math3/geometry/spherical/oned/LimitAngle" sourcefilename="LimitAngle.java">
            <method desc="(Lorg/apache/commons/math3/geometry/spherical/oned/S1Point;ZD)V" line="44" name="&lt;init&gt;">
                <counter covered="0" missed="12" type="INSTRUCTION"/>
                <counter covered="0" missed="5" type="LINE"/>
                <counter covered="0" missed="1" type="COMPLEXITY"/>
                <counter covered="0" missed="1" type="METHOD"/>
            </method>
            <method desc="()Lorg/apache/commons/math3/geometry/spherical/oned/LimitAngle;" line="56" name="copySelf">
                <counter covered="0" missed="2" type="INSTRUCTION"/>
                <counter covered="0" missed="1" type="LINE"/>
                <counter covered="0" missed="1" type="COMPLEXITY"/>
                <counter covered="0" missed="1" type="METHOD"/>
            </method>
            <method desc="(Lorg/apache/commons/math3/geometry/Point;)D" line="61" name="getOffset">
                <counter covered="0" missed="16" type="INSTRUCTION"/>
                <counter covered="0" missed="2" type="BRANCH"/>
                <counter covered="0" missed="2" type="LINE"/>
                <counter covered="0" missed="2" type="COMPLEXITY"/>
                <counter covered="0" missed="1" type="METHOD"/>
            </method>
            <method desc="()Z" line="70" name="isDirect">
                <counter covered="0" missed="3" type="INSTRUCTION"/>
                <counter covered="0" missed="1" type="LINE"/>
                <counter covered="0" missed="1" type="COMPLEXITY"/>
                <counter covered="0" missed="1" type="METHOD"/>
            </method>
            <method desc="()Lorg/apache/commons/math3/geometry/spherical/oned/LimitAngle;" line="79" name="getReverse">
                <counter covered="0" missed="14" type="INSTRUCTION"/>
                <counter covered="0" missed="2" type="BRANCH"/>
                <counter covered="0" missed="1" type="LINE"/>
                <counter covered="0" missed="2" type="COMPLEXITY"/>
                <counter covered="0" missed="1" type="METHOD"/>
            </method>
            <method desc="()Lorg/apache/commons/math3/geometry/spherical/oned/SubLimitAngle;" line="94" name="wholeHyperplane">
                <counter covered="0" missed="6" type="INSTRUCTION"/>
                <counter covered="0" missed="1" type="LINE"/>
                <counter covered="0" missed="1" type="COMPLEXITY"/>
                <counter covered="0" missed="1" type="METHOD"/>
            </method>
            <method desc="()Lorg/apache/commons/math3/geometry/spherical/oned/ArcsSet;" line="102" name="wholeSpace">
                <counter covered="0" missed="6" type="INSTRUCTION"/>
                <counter covered="0" missed="1" type="LINE"/>
                <counter covered="0" missed="1" type="COMPLEXITY"/>
                <counter covered="0" missed="1" type="METHOD"/>
            </method>
            <method desc="(Lorg/apache/commons/math3/geometry/partitioning/Hyperplane;)Z" line="107" name="sameOrientationAs">
                <counter covered="0" missed="11" type="INSTRUCTION"/>
                <counter covered="0" missed="2" type="BRANCH"/>
                <counter covered="0" missed="1" type="LINE"/>
                <counter covered="0" missed="2" type="COMPLEXITY"/>
                <counter covered="0" missed="1" type="METHOD"/>
            </method>
            <method desc="()Lorg/apache/commons/math3/geometry/spherical/oned/S1Point;" line="114" name="getLocation">
                <counter covered="0" missed="3" type="INSTRUCTION"/>
                <counter covered="0" missed="1" type="LINE"/>
                <counter covered="0" missed="1" type="COMPLEXITY"/>
                <counter covered="0" missed="1" type="METHOD"/>
            </method>
            <method desc="(Lorg/apache/commons/math3/geometry/Point;)Lorg/apache/commons/math3/geometry/Point;" line="119" name="project">
                <counter covered="0" missed="3" type="INSTRUCTION"/>
                <counter covered="0" missed="1" type="LINE"/>
                <counter covered="0" missed="1" type="COMPLEXITY"/>
                <counter covered="0" missed="1" type="METHOD"/>
            </method>
            <method desc="()D" line="124" name="getTolerance">
                <counter covered="0" missed="3" type="INSTRUCTION"/>
                <counter covered="0" missed="1" type="LINE"/>
                <counter covered="0" missed="1" type="COMPLEXITY"/>
                <counter covered="0" missed="1" type="METHOD"/>
            </method>
            <counter covered="0" missed="79" type="INSTRUCTION"/>
            <counter covered="0" missed="6" type="BRANCH"/>
            <counter covered="0" missed="16" type="LINE"/>
            <counter covered="0" missed="14" type="COMPLEXITY"/>
            <counter covered="0" missed="11" type="METHOD"/>
            <counter covered="0" missed="1" type="CLASS"/>
        </class>
        <class name="org/apache/commons/math3/geometry/spherical/oned/Sphere1D$LazyHolder" sourcefilename="Sphere1D.java">
            <method desc="()V" line="76" name="&lt;clinit&gt;">
                <counter covered="0" missed="6" type="INSTRUCTION"/>
                <counter covered="0" missed="1" type="LINE"/>
                <counter covered="0" missed="1" type="COMPLEXITY"/>
                <counter covered="0" missed="1" type="METHOD"/>
            </method>
            <counter covered="0" missed="6" type="INSTRUCTION"/>
            <counter covered="0" missed="1" type="LINE"/>
            <counter covered="0" missed="1" type="COMPLEXITY"/>
            <counter covered="0" missed="1" type="METHOD"/>
            <counter covered="0" missed="1" type="CLASS"/>
        </class>
        <class name="org/apache/commons/math3/geometry/spherical/oned/Sphere1D" sourcefilename="Sphere1D.java">
            <method desc="()Lorg/apache/commons/math3/geometry/spherical/oned/Sphere1D;" line="50" name="getInstance">
                <counter covered="0" missed="2" type="INSTRUCTION"/>
                <counter covered="0" missed="1" type="LINE"/>
                <counter covered="0" missed="1" type="COMPLEXITY"/>
                <counter covered="0" missed="1" type="METHOD"/>
            </method>
            <method desc="()I" line="55" name="getDimension">
                <counter covered="0" missed="2" type="INSTRUCTION"/>
                <counter covered="0" missed="1" type="LINE"/>
                <counter covered="0" missed="1" type="COMPLEXITY"/>
                <counter covered="0" missed="1" type="METHOD"/>
            </method>
            <method desc="()Lorg/apache/commons/math3/geometry/Space;" line="67" name="getSubSpace">
                <counter covered="0" missed="4" type="INSTRUCTION"/>
                <counter covered="0" missed="1" type="LINE"/>
                <counter covered="0" missed="1" type="COMPLEXITY"/>
                <counter covered="0" missed="1" type="METHOD"/>
            </method>
            <method desc="()Ljava/lang/Object;" line="85" name="readResolve">
                <counter covered="0" missed="2" type="INSTRUCTION"/>
                <counter covered="0" missed="1" type="LINE"/>
                <counter covered="0" missed="1" type="COMPLEXITY"/>
                <counter covered="0" missed="1" type="METHOD"/>
            </method>
            <counter covered="0" missed="10" type="INSTRUCTION"/>
            <counter covered="0" missed="4" type="LINE"/>
            <counter covered="0" missed="4" type="COMPLEXITY"/>
            <counter covered="0" missed="4" type="METHOD"/>
            <counter covered="0" missed="1" type="CLASS"/>
        </class>
        <class name="org/apache/commons/math3/geometry/spherical/oned/ArcsSet$InconsistentStateAt2PiWrapping" sourcefilename="ArcsSet.java">
            <method desc="()V" line="950" name="&lt;init&gt;">
                <counter covered="0" missed="6" type="INSTRUCTION"/>
                <counter covered="0" missed="2" type="LINE"/>
                <counter covered="0" missed="1" type="COMPLEXITY"/>
                <counter covered="0" missed="1" type="METHOD"/>
            </method>
            <counter covered="0" missed="6" type="INSTRUCTION"/>
            <counter covered="0" missed="2" type="LINE"/>
            <counter covered="0" missed="1" type="COMPLEXITY"/>
            <counter covered="0" missed="1" type="METHOD"/>
            <counter covered="0" missed="1" type="CLASS"/>
        </class>
        <class name="org/apache/commons/math3/geometry/spherical/oned/ArcsSet$SubArcsIterator" sourcefilename="ArcsSet.java">
            <method desc="(Lorg/apache/commons/math3/geometry/spherical/oned/ArcsSet;)V" line="601" name="&lt;init&gt;">
                <counter covered="0" missed="45" type="INSTRUCTION"/>
                <counter covered="0" missed="4" type="BRANCH"/>
                <counter covered="0" missed="9" type="LINE"/>
                <counter covered="0" missed="3" type="COMPLEXITY"/>
                <counter covered="0" missed="1" type="METHOD"/>
            </method>
            <method desc="()V" line="626" name="selectPending">
                <counter covered="0" missed="110" type="INSTRUCTION"/>
                <counter covered="0" missed="18" type="BRANCH"/>
                <counter covered="0" missed="21" type="LINE"/>
                <counter covered="0" missed="10" type="COMPLEXITY"/>
                <counter covered="0" missed="1" type="METHOD"/>
            </method>
            <method desc="()Z" line="680" name="hasNext">
                <counter covered="0" missed="7" type="INSTRUCTION"/>
                <counter covered="0" missed="2" type="BRANCH"/>
                <counter covered="0" missed="1" type="LINE"/>
                <counter covered="0" missed="2" type="COMPLEXITY"/>
                <counter covered="0" missed="1" type="METHOD"/>
            </method>
            <method desc="()[D" line="685" name="next">
                <counter covered="0" missed="14" type="INSTRUCTION"/>
                <counter covered="0" missed="2" type="BRANCH"/>
                <counter covered="0" missed="5" type="LINE"/>
                <counter covered="0" missed="2" type="COMPLEXITY"/>
                <counter covered="0" missed="1" type="METHOD"/>
            </method>
            <method desc="()V" line="695" name="remove">
                <counter covered="0" missed="4" type="INSTRUCTION"/>
                <counter covered="0" missed="1" type="LINE"/>
                <counter covered="0" missed="1" type="COMPLEXITY"/>
                <counter covered="0" missed="1" type="METHOD"/>
            </method>
            <counter covered="0" missed="180" type="INSTRUCTION"/>
            <counter covered="0" missed="26" type="BRANCH"/>
            <counter covered="0" missed="37" type="LINE"/>
            <counter covered="0" missed="18" type="COMPLEXITY"/>
            <counter covered="0" missed="5" type="METHOD"/>
            <counter covered="0" missed="1" type="CLASS"/>
        </class>
        <class name="org/apache/commons/math3/geometry/spherical/oned/ArcsSet$Split" sourcefilename="ArcsSet.java">
            <method desc="(Lorg/apache/commons/math3/geometry/spherical/oned/ArcsSet;Lorg/apache/commons/math3/geometry/spherical/oned/ArcsSet;)V" line="892" name="&lt;init&gt;">
                <counter covered="0" missed="9" type="INSTRUCTION"/>
                <counter covered="0" missed="4" type="LINE"/>
                <counter covered="0" missed="1" type="COMPLEXITY"/>
                <counter covered="0" missed="1" type="METHOD"/>
            </method>
            <method desc="()Lorg/apache/commons/math3/geometry/spherical/oned/ArcsSet;" line="901" name="getPlus">
                <counter covered="0" missed="3" type="INSTRUCTION"/>
                <counter covered="0" missed="1" type="LINE"/>
                <counter covered="0" missed="1" type="COMPLEXITY"/>
                <counter covered="0" missed="1" type="METHOD"/>
            </method>
            <method desc="()Lorg/apache/commons/math3/geometry/spherical/oned/ArcsSet;" line="908" name="getMinus">
                <counter covered="0" missed="3" type="INSTRUCTION"/>
                <counter covered="0" missed="1" type="LINE"/>
                <counter covered="0" missed="1" type="COMPLEXITY"/>
                <counter covered="0" missed="1" type="METHOD"/>
            </method>
            <method desc="()Lorg/apache/commons/math3/geometry/partitioning/Side;" line="920" name="getSide">
                <counter covered="0" missed="17" type="INSTRUCTION"/>
                <counter covered="0" missed="6" type="BRANCH"/>
                <counter covered="0" missed="7" type="LINE"/>
                <counter covered="0" missed="4" type="COMPLEXITY"/>
                <counter covered="0" missed="1" type="METHOD"/>
            </method>
            <counter covered="0" missed="32" type="INSTRUCTION"/>
            <counter covered="0" missed="6" type="BRANCH"/>
            <counter covered="0" missed="13" type="LINE"/>
            <counter covered="0" missed="7" type="COMPLEXITY"/>
            <counter covered="0" missed="4" type="METHOD"/>
            <counter covered="0" missed="1" type="CLASS"/>
        </class>
        <class name="org/apache/commons/math3/geometry/spherical/oned/ArcsSet" sourcefilename="ArcsSet.java">
            <method desc="(D)V" line="55" name="&lt;init&gt;">
                <counter covered="0" missed="4" type="INSTRUCTION"/>
                <counter covered="0" missed="2" type="LINE"/>
                <counter covered="0" missed="1" type="COMPLEXITY"/>
                <counter covered="0" missed="1" type="METHOD"/>
            </method>
            <method desc="(DDD)V" line="73" name="&lt;init&gt;">
                <counter covered="0" missed="8" type="INSTRUCTION"/>
                <counter covered="0" missed="2" type="LINE"/>
                <counter covered="0" missed="1" type="COMPLEXITY"/>
                <counter covered="0" missed="1" type="METHOD"/>
            </method>
            <method desc="(Lorg/apache/commons/math3/geometry/partitioning/BSPTree;D)V" line="90" name="&lt;init&gt;">
                <counter covered="0" missed="7" type="INSTRUCTION"/>
                <counter covered="0" missed="3" type="LINE"/>
                <counter covered="0" missed="1" type="COMPLEXITY"/>
                <counter covered="0" missed="1" type="METHOD"/>
            </method>
            <method desc="(Ljava/util/Collection;D)V" line="118" name="&lt;init&gt;">
                <counter covered="0" missed="7" type="INSTRUCTION"/>
                <counter covered="0" missed="3" type="LINE"/>
                <counter covered="0" missed="1" type="COMPLEXITY"/>
                <counter covered="0" missed="1" type="METHOD"/>
            </method>
            <method desc="(DDD)Lorg/apache/commons/math3/geometry/partitioning/BSPTree;" line="133" name="buildTree">
                <counter covered="0" missed="125" type="INSTRUCTION"/>
                <counter covered="0" missed="8" type="BRANCH"/>
                <counter covered="0" missed="12" type="LINE"/>
                <counter covered="0" missed="5" type="COMPLEXITY"/>
                <counter covered="0" missed="1" type="METHOD"/>
            </method>
            <method desc="()V" line="180" name="check2PiConsistency">
                <counter covered="0" missed="31" type="INSTRUCTION"/>
                <counter covered="0" missed="4" type="BRANCH"/>
                <counter covered="0" missed="8" type="LINE"/>
                <counter covered="0" missed="3" type="COMPLEXITY"/>
                <counter covered="0" missed="1" type="METHOD"/>
            </method>
            <method desc="(Lorg/apache/commons/math3/geometry/partitioning/BSPTree;)Lorg/apache/commons/math3/geometry/partitioning/BSPTree;" line="203" name="getFirstLeaf">
                <counter covered="0" missed="22" type="INSTRUCTION"/>
                <counter covered="0" missed="4" type="BRANCH"/>
                <counter covered="0" missed="6" type="LINE"/>
                <counter covered="0" missed="3" type="COMPLEXITY"/>
                <counter covered="0" missed="1" type="METHOD"/>
            </method>
            <method desc="(Lorg/apache/commons/math3/geometry/partitioning/BSPTree;)Lorg/apache/commons/math3/geometry/partitioning/BSPTree;" line="223" name="getLastLeaf">
                <counter covered="0" missed="22" type="INSTRUCTION"/>
                <counter covered="0" missed="4" type="BRANCH"/>
                <counter covered="0" missed="6" type="LINE"/>
                <counter covered="0" missed="3" type="COMPLEXITY"/>
                <counter covered="0" missed="1" type="METHOD"/>
            </method>
            <method desc="()Lorg/apache/commons/math3/geometry/partitioning/BSPTree;" line="244" name="getFirstArcStart">
                <counter covered="0" missed="27" type="INSTRUCTION"/>
                <counter covered="0" missed="6" type="BRANCH"/>
                <counter covered="0" missed="7" type="LINE"/>
                <counter covered="0" missed="4" type="COMPLEXITY"/>
                <counter covered="0" missed="1" type="METHOD"/>
            </method>
            <method desc="(Lorg/apache/commons/math3/geometry/partitioning/BSPTree;)Z" line="267" name="isArcStart">
                <counter covered="0" missed="20" type="INSTRUCTION"/>
                <counter covered="0" missed="4" type="BRANCH"/>
                <counter covered="0" missed="5" type="LINE"/>
                <counter covered="0" missed="3" type="COMPLEXITY"/>
                <counter covered="0" missed="1" type="METHOD"/>
            </method>
            <method desc="(Lorg/apache/commons/math3/geometry/partitioning/BSPTree;)Z" line="289" name="isArcEnd">
                <counter covered="0" missed="20" type="INSTRUCTION"/>
                <counter covered="0" missed="4" type="BRANCH"/>
                <counter covered="0" missed="5" type="LINE"/>
                <counter covered="0" missed="3" type="COMPLEXITY"/>
                <counter covered="0" missed="1" type="METHOD"/>
            </method>
            <method desc="(Lorg/apache/commons/math3/geometry/partitioning/BSPTree;)Lorg/apache/commons/math3/geometry/partitioning/BSPTree;" line="312" name="nextInternalNode">
                <counter covered="0" missed="21" type="INSTRUCTION"/>
                <counter covered="0" missed="4" type="BRANCH"/>
                <counter covered="0" missed="5" type="LINE"/>
                <counter covered="0" missed="3" type="COMPLEXITY"/>
                <counter covered="0" missed="1" type="METHOD"/>
            </method>
            <method desc="(Lorg/apache/commons/math3/geometry/partitioning/BSPTree;)Lorg/apache/commons/math3/geometry/partitioning/BSPTree;" line="332" name="previousInternalNode">
                <counter covered="0" missed="21" type="INSTRUCTION"/>
                <counter covered="0" missed="4" type="BRANCH"/>
                <counter covered="0" missed="5" type="LINE"/>
                <counter covered="0" missed="3" type="COMPLEXITY"/>
                <counter covered="0" missed="1" type="METHOD"/>
            </method>
            <method desc="(Lorg/apache/commons/math3/geometry/partitioning/BSPTree;)Lorg/apache/commons/math3/geometry/partitioning/BSPTree;" line="351" name="leafBefore">
                <counter covered="0" missed="14" type="INSTRUCTION"/>
                <counter covered="0" missed="2" type="BRANCH"/>
                <counter covered="0" missed="4" type="LINE"/>
                <counter covered="0" missed="2" type="COMPLEXITY"/>
                <counter covered="0" missed="1" type="METHOD"/>
            </method>
            <method desc="(Lorg/apache/commons/math3/geometry/partitioning/BSPTree;)Lorg/apache/commons/math3/geometry/partitioning/BSPTree;" line="366" name="leafAfter">
                <counter covered="0" missed="14" type="INSTRUCTION"/>
                <counter covered="0" missed="2" type="BRANCH"/>
                <counter covered="0" missed="4" type="LINE"/>
                <counter covered="0" missed="2" type="COMPLEXITY"/>
                <counter covered="0" missed="1" type="METHOD"/>
            </method>
            <method desc="(Lorg/apache/commons/math3/geometry/partitioning/BSPTree;)Z" line="380" name="isBeforeParent">
                <counter covered="0" missed="16" type="INSTRUCTION"/>
                <counter covered="0" missed="4" type="BRANCH"/>
                <counter covered="0" missed="4" type="LINE"/>
                <counter covered="0" missed="3" type="COMPLEXITY"/>
                <counter covered="0" missed="1" type="METHOD"/>
            </method>
            <method desc="(Lorg/apache/commons/math3/geometry/partitioning/BSPTree;)Z" line="393" name="isAfterParent">
                <counter covered="0" missed="16" type="INSTRUCTION"/>
                <counter covered="0" missed="4" type="BRANCH"/>
                <counter covered="0" missed="4" type="LINE"/>
                <counter covered="0" missed="3" type="COMPLEXITY"/>
                <counter covered="0" missed="1" type="METHOD"/>
            </method>
            <method desc="(Lorg/apache/commons/math3/geometry/partitioning/BSPTree;)Lorg/apache/commons/math3/geometry/partitioning/BSPTree;" line="406" name="childBefore">
                <counter covered="0" missed="10" type="INSTRUCTION"/>
                <counter covered="0" missed="2" type="BRANCH"/>
                <counter covered="0" missed="3" type="LINE"/>
                <counter covered="0" missed="2" type="COMPLEXITY"/>
                <counter covered="0" missed="1" type="METHOD"/>
            </method>
            <method desc="(Lorg/apache/commons/math3/geometry/partitioning/BSPTree;)Lorg/apache/commons/math3/geometry/partitioning/BSPTree;" line="420" name="childAfter">
                <counter covered="0" missed="10" type="INSTRUCTION"/>
                <counter covered="0" missed="2" type="BRANCH"/>
                <counter covered="0" missed="3" type="LINE"/>
                <counter covered="0" missed="2" type="COMPLEXITY"/>
                <counter covered="0" missed="1" type="METHOD"/>
            </method>
            <method desc="(Lorg/apache/commons/math3/geometry/partitioning/BSPTree;)Z" line="434" name="isDirect">
                <counter covered="0" missed="6" type="INSTRUCTION"/>
                <counter covered="0" missed="1" type="LINE"/>
                <counter covered="0" missed="1" type="COMPLEXITY"/>
                <counter covered="0" missed="1" type="METHOD"/>
            </method>
            <method desc="(Lorg/apache/commons/math3/geometry/partitioning/BSPTree;)D" line="442" name="getAngle">
                <counter covered="0" missed="7" type="INSTRUCTION"/>
                <counter covered="0" missed="1" type="LINE"/>
                <counter covered="0" missed="1" type="COMPLEXITY"/>
                <counter covered="0" missed="1" type="METHOD"/>
            </method>
            <method desc="(Lorg/apache/commons/math3/geometry/partitioning/BSPTree;)Lorg/apache/commons/math3/geometry/spherical/oned/ArcsSet;" line="448" name="buildNew">
                <counter covered="0" missed="7" type="INSTRUCTION"/>
                <counter covered="0" missed="1" type="LINE"/>
                <counter covered="0" missed="1" type="COMPLEXITY"/>
                <counter covered="0" missed="1" type="METHOD"/>
            </method>
            <method desc="()V" line="454" name="computeGeometricalProperties">
                <counter covered="0" missed="99" type="INSTRUCTION"/>
                <counter covered="0" missed="10" type="BRANCH"/>
                <counter covered="0" missed="18" type="LINE"/>
                <counter covered="0" missed="6" type="COMPLEXITY"/>
                <counter covered="0" missed="1" type="METHOD"/>
            </method>
            <method desc="(Lorg/apache/commons/math3/geometry/Point;)Lorg/apache/commons/math3/geometry/partitioning/BoundaryProjection;" line="484" name="projectToBoundary">
                <counter covered="0" missed="208" type="INSTRUCTION"/>
                <counter covered="0" missed="24" type="BRANCH"/>
                <counter covered="0" missed="37" type="LINE"/>
                <counter covered="0" missed="13" type="COMPLEXITY"/>
                <counter covered="0" missed="1" type="METHOD"/>
            </method>
            <method desc="()Ljava/util/List;" line="568" name="asList">
                <counter covered="0" missed="31" type="INSTRUCTION"/>
                <counter covered="0" missed="2" type="BRANCH"/>
                <counter covered="0" missed="5" type="LINE"/>
                <counter covered="0" missed="2" type="COMPLEXITY"/>
                <counter covered="0" missed="1" type="METHOD"/>
            </method>
            <method desc="()Ljava/util/Iterator;" line="584" name="iterator">
                <counter covered="0" missed="5" type="INSTRUCTION"/>
                <counter covered="0" missed="1" type="LINE"/>
                <counter covered="0" missed="1" type="COMPLEXITY"/>
                <counter covered="0" missed="1" type="METHOD"/>
            </method>
            <method desc="(Lorg/apache/commons/math3/geometry/spherical/oned/Arc;)Lorg/apache/commons/math3/geometry/partitioning/Side;" line="712" name="side">
                <counter covered="0" missed="5" type="INSTRUCTION"/>
                <counter covered="0" missed="1" type="LINE"/>
                <counter covered="0" missed="1" type="COMPLEXITY"/>
                <counter covered="0" missed="1" type="METHOD"/>
            </method>
            <method desc="(Lorg/apache/commons/math3/geometry/spherical/oned/Arc;)Lorg/apache/commons/math3/geometry/spherical/oned/ArcsSet$Split;" line="723" name="split">
                <counter covered="0" missed="203" type="INSTRUCTION"/>
                <counter covered="0" missed="12" type="BRANCH"/>
                <counter covered="0" missed="39" type="LINE"/>
                <counter covered="0" missed="7" type="COMPLEXITY"/>
                <counter covered="0" missed="1" type="METHOD"/>
            </method>
            <method desc="(Lorg/apache/commons/math3/geometry/partitioning/BSPTree;DZ)V" line="795" name="addArcLimit">
                <counter covered="0" missed="45" type="INSTRUCTION"/>
                <counter covered="0" missed="4" type="BRANCH"/>
                <counter covered="0" missed="9" type="LINE"/>
                <counter covered="0" missed="3" type="COMPLEXITY"/>
                <counter covered="0" missed="1" type="METHOD"/>
            </method>
            <method desc="(Ljava/util/List;)Lorg/apache/commons/math3/geometry/spherical/oned/ArcsSet;" line="819" name="createSplitPart">
                <counter covered="0" missed="151" type="INSTRUCTION"/>
                <counter covered="0" missed="16" type="BRANCH"/>
                <counter covered="0" missed="25" type="LINE"/>
                <counter covered="0" missed="9" type="COMPLEXITY"/>
                <counter covered="0" missed="1" type="METHOD"/>
            </method>
            <counter covered="0" missed="1182" type="INSTRUCTION"/>
            <counter covered="0" missed="126" type="BRANCH"/>
            <counter covered="0" missed="229" type="LINE"/>
            <counter covered="0" missed="93" type="COMPLEXITY"/>
            <counter covered="0" missed="30" type="METHOD"/>
            <counter covered="0" missed="1" type="CLASS"/>
        </class>
        <class name="org/apache/commons/math3/geometry/spherical/oned/Arc" sourcefilename="Arc.java">
            <method desc="(DDD)V" line="62" name="&lt;init&gt;">
                <counter covered="0" missed="64" type="INSTRUCTION"/>
                <counter covered="0" missed="6" type="BRANCH"/>
                <counter covered="0" missed="12" type="LINE"/>
                <counter covered="0" missed="4" type="COMPLEXITY"/>
                <counter covered="0" missed="1" type="METHOD"/>
            </method>
            <method desc="()D" line="84" name="getInf">
                <counter covered="0" missed="3" type="INSTRUCTION"/>
                <counter covered="0" missed="1" type="LINE"/>
                <counter covered="0" missed="1" type="COMPLEXITY"/>
                <counter covered="0" missed="1" type="METHOD"/>
            </method>
            <method desc="()D" line="92" name="getSup">
                <counter covered="0" missed="3" type="INSTRUCTION"/>
                <counter covered="0" missed="1" type="LINE"/>
                <counter covered="0" missed="1" type="COMPLEXITY"/>
                <counter covered="0" missed="1" type="METHOD"/>
            </method>
            <method desc="()D" line="99" name="getSize">
                <counter covered="0" missed="6" type="INSTRUCTION"/>
                <counter covered="0" missed="1" type="LINE"/>
                <counter covered="0" missed="1" type="COMPLEXITY"/>
                <counter covered="0" missed="1" type="METHOD"/>
            </method>
            <method desc="()D" line="106" name="getBarycenter">
                <counter covered="0" missed="3" type="INSTRUCTION"/>
                <counter covered="0" missed="1" type="LINE"/>
                <counter covered="0" missed="1" type="COMPLEXITY"/>
                <counter covered="0" missed="1" type="METHOD"/>
            </method>
            <method desc="()D" line="113" name="getTolerance">
                <counter covered="0" missed="3" type="INSTRUCTION"/>
                <counter covered="0" missed="1" type="LINE"/>
                <counter covered="0" missed="1" type="COMPLEXITY"/>
                <counter covered="0" missed="1" type="METHOD"/>
            </method>
            <method desc="(D)Lorg/apache/commons/math3/geometry/partitioning/Region$Location;" line="122" name="checkPoint">
                <counter covered="0" missed="53" type="INSTRUCTION"/>
                <counter covered="0" missed="10" type="BRANCH"/>
                <counter covered="0" missed="6" type="LINE"/>
                <counter covered="0" missed="6" type="COMPLEXITY"/>
                <counter covered="0" missed="1" type="METHOD"/>
            </method>
            <counter covered="0" missed="135" type="INSTRUCTION"/>
            <counter covered="0" missed="16" type="BRANCH"/>
            <counter covered="0" missed="23" type="LINE"/>
            <counter covered="0" missed="15" type="COMPLEXITY"/>
            <counter covered="0" missed="7" type="METHOD"/>
            <counter covered="0" missed="1" type="CLASS"/>
        </class>
        <class name="org/apache/commons/math3/geometry/spherical/oned/Sphere1D$NoSubSpaceException" sourcefilename="Sphere1D.java">
            <method desc="()V" line="101" name="&lt;init&gt;">
                <counter covered="0" missed="11" type="INSTRUCTION"/>
                <counter covered="0" missed="2" type="LINE"/>
                <counter covered="0" missed="1" type="COMPLEXITY"/>
                <counter covered="0" missed="1" type="METHOD"/>
            </method>
            <counter covered="0" missed="11" type="INSTRUCTION"/>
            <counter covered="0" missed="2" type="LINE"/>
            <counter covered="0" missed="1" type="COMPLEXITY"/>
            <counter covered="0" missed="1" type="METHOD"/>
            <counter covered="0" missed="1" type="CLASS"/>
        </class>
        <sourcefile name="Arc.java">
            <line cb="0" ci="0" mb="0" mi="2" nr="62"/>
            <line cb="0" ci="0" mb="0" mi="3" nr="63"/>
            <line cb="0" ci="0" mb="4" mi="11" nr="64"/>
            <line cb="0" ci="0" mb="0" mi="3" nr="66"/>
            <line cb="0" ci="0" mb="0" mi="3" nr="67"/>
            <line cb="0" ci="0" mb="0" mi="4" nr="68"/>
            <line cb="0" ci="0" mb="2" mi="4" nr="69"/>
            <line cb="0" ci="0" mb="0" mi="5" nr="70"/>
            <line cb="0" ci="0" mb="0" mi="8" nr="71"/>
            <line cb="0" ci="0" mb="0" mi="10" nr="72"/>
            <line cb="0" ci="0" mb="0" mi="10" nr="74"/>
            <line cb="0" ci="0" mb="0" mi="1" nr="77"/>
            <line cb="0" ci="0" mb="0" mi="3" nr="84"/>
            <line cb="0" ci="0" mb="0" mi="3" nr="92"/>
            <line cb="0" ci="0" mb="0" mi="6" nr="99"/>
            <line cb="0" ci="0" mb="0" mi="3" nr="106"/>
            <line cb="0" ci="0" mb="0" mi="3" nr="113"/>
            <line cb="0" ci="0" mb="0" mi="5" nr="122"/>
            <line cb="0" ci="0" mb="4" mi="16" nr="123"/>
            <line cb="0" ci="0" mb="0" mi="2" nr="124"/>
            <line cb="0" ci="0" mb="4" mi="16" nr="125"/>
            <line cb="0" ci="0" mb="0" mi="2" nr="126"/>
            <line cb="0" ci="0" mb="2" mi="12" nr="128"/>
            <counter covered="0" missed="135" type="INSTRUCTION"/>
            <counter covered="0" missed="16" type="BRANCH"/>
            <counter covered="0" missed="23" type="LINE"/>
            <counter covered="0" missed="15" type="COMPLEXITY"/>
            <counter covered="0" missed="7" type="METHOD"/>
            <counter covered="0" missed="1" type="CLASS"/>
        </sourcefile>
        <sourcefile name="LimitAngle.java">
            <line cb="0" ci="0" mb="0" mi="2" nr="44"/>
            <line cb="0" ci="0" mb="0" mi="3" nr="45"/>
            <line cb="0" ci="0" mb="0" mi="3" nr="46"/>
            <line cb="0" ci="0" mb="0" mi="3" nr="47"/>
            <line cb="0" ci="0" mb="0" mi="1" nr="48"/>
            <line cb="0" ci="0" mb="0" mi="2" nr="56"/>
            <line cb="0" ci="0" mb="0" mi="8" nr="61"/>
            <line cb="0" ci="0" mb="2" mi="8" nr="62"/>
            <line cb="0" ci="0" mb="0" mi="3" nr="70"/>
            <line cb="0" ci="0" mb="2" mi="14" nr="79"/>
            <line cb="0" ci="0" mb="0" mi="6" nr="94"/>
            <line cb="0" ci="0" mb="0" mi="6" nr="102"/>
            <line cb="0" ci="0" mb="2" mi="11" nr="107"/>
            <line cb="0" ci="0" mb="0" mi="3" nr="114"/>
            <line cb="0" ci="0" mb="0" mi="3" nr="119"/>
            <line cb="0" ci="0" mb="0" mi="3" nr="124"/>
            <counter covered="0" missed="79" type="INSTRUCTION"/>
            <counter covered="0" missed="6" type="BRANCH"/>
            <counter covered="0" missed="16" type="LINE"/>
            <counter covered="0" missed="14" type="COMPLEXITY"/>
            <counter covered="0" missed="11" type="METHOD"/>
            <counter covered="0" missed="1" type="CLASS"/>
        </sourcefile>
        <sourcefile name="SubLimitAngle.java">
            <line cb="0" ci="0" mb="0" mi="4" nr="35"/>
            <line cb="0" ci="0" mb="0" mi="1" nr="36"/>
            <line cb="0" ci="0" mb="0" mi="2" nr="41"/>
            <line cb="0" ci="0" mb="0" mi="2" nr="47"/>
            <line cb="0" ci="0" mb="0" mi="6" nr="54"/>
            <line cb="0" ci="0" mb="0" mi="7" nr="60"/>
            <line cb="0" ci="0" mb="2" mi="16" nr="61"/>
            <counter covered="0" missed="38" type="INSTRUCTION"/>
            <counter covered="0" missed="2" type="BRANCH"/>
            <counter covered="0" missed="7" type="LINE"/>
            <counter covered="0" missed="6" type="COMPLEXITY"/>
            <counter covered="0" missed="5" type="METHOD"/>
            <counter covered="0" missed="1" type="CLASS"/>
        </sourcefile>
        <sourcefile name="ArcsSet.java">
            <line cb="0" ci="0" mb="0" mi="3" nr="55"/>
            <line cb="0" ci="0" mb="0" mi="1" nr="56"/>
            <line cb="0" ci="0" mb="0" mi="7" nr="73"/>
            <line cb="0" ci="0" mb="0" mi="1" nr="74"/>
            <line cb="0" ci="0" mb="0" mi="4" nr="90"/>
            <line cb="0" ci="0" mb="0" mi="2" nr="91"/>
            <line cb="0" ci="0" mb="0" mi="1" nr="92"/>
            <line cb="0" ci="0" mb="0" mi="4" nr="118"/>
            <line cb="0" ci="0" mb="0" mi="2" nr="119"/>
            <line cb="0" ci="0" mb="0" mi="1" nr="120"/>
            <line cb="0" ci="0" mb="4" mi="11" nr="133"/>
            <line cb="0" ci="0" mb="0" mi="5" nr="135"/>
            <line cb="0" ci="0" mb="2" mi="4" nr="136"/>
            <line cb="0" ci="0" mb="0" mi="10" nr="137"/>
            <line cb="0" ci="0" mb="0" mi="4" nr="142"/>
            <line cb="0" ci="0" mb="0" mi="6" nr="143"/>
            <line cb="0" ci="0" mb="0" mi="11" nr="144"/>
            <line cb="0" ci="0" mb="2" mi="4" nr="147"/>
            <line cb="0" ci="0" mb="0" mi="11" nr="149"/>
            <line cb="0" ci="0" mb="0" mi="23" nr="151"/>
            <line cb="0" ci="0" mb="0" mi="13" nr="160"/>
            <line cb="0" ci="0" mb="0" mi="23" nr="162"/>
            <line cb="0" ci="0" mb="0" mi="4" nr="180"/>
            <line cb="0" ci="0" mb="2" mi="3" nr="181"/>
            <line cb="0" ci="0" mb="0" mi="1" nr="182"/>
            <line cb="0" ci="0" mb="0" mi="6" nr="186"/>
            <line cb="0" ci="0" mb="0" mi="6" nr="189"/>
            <line cb="0" ci="0" mb="2" mi="6" nr="191"/>
            <line cb="0" ci="0" mb="0" mi="4" nr="192"/>
            <line cb="0" ci="0" mb="0" mi="1" nr="195"/>
            <line cb="0" ci="0" mb="2" mi="3" nr="203"/>
            <line cb="0" ci="0" mb="0" mi="2" nr="204"/>
            <line cb="0" ci="0" mb="0" mi="2" nr="208"/>
            <line cb="0" ci="0" mb="2" mi="9" nr="209"/>
            <line cb="0" ci="0" mb="0" mi="2" nr="210"/>
            <line cb="0" ci="0" mb="0" mi="4" nr="213"/>
            <line cb="0" ci="0" mb="2" mi="3" nr="223"/>
            <line cb="0" ci="0" mb="0" mi="2" nr="224"/>
            <line cb="0" ci="0" mb="0" mi="2" nr="228"/>
            <line cb="0" ci="0" mb="2" mi="9" nr="229"/>
            <line cb="0" ci="0" mb="0" mi="2" nr="230"/>
            <line cb="0" ci="0" mb="0" mi="4" nr="233"/>
            <line cb="0" ci="0" mb="0" mi="4" nr="244"/>
            <line cb="0" ci="0" mb="2" mi="3" nr="245"/>
            <line cb="0" ci="0" mb="0" mi="2" nr="246"/>
            <line cb="0" ci="0" mb="0" mi="5" nr="250"/>
            <line cb="0" ci="0" mb="4" mi="6" nr="253"/>
            <line cb="0" ci="0" mb="0" mi="5" nr="254"/>
            <line cb="0" ci="0" mb="0" mi="2" nr="257"/>
            <line cb="0" ci="0" mb="2" mi="7" nr="267"/>
            <line cb="0" ci="0" mb="0" mi="2" nr="269"/>
            <line cb="0" ci="0" mb="2" mi="7" nr="272"/>
            <line cb="0" ci="0" mb="0" mi="2" nr="274"/>
            <line cb="0" ci="0" mb="0" mi="2" nr="279"/>
            <line cb="0" ci="0" mb="2" mi="7" nr="289"/>
            <line cb="0" ci="0" mb="0" mi="2" nr="291"/>
            <line cb="0" ci="0" mb="2" mi="7" nr="294"/>
            <line cb="0" ci="0" mb="0" mi="2" nr="296"/>
            <line cb="0" ci="0" mb="0" mi="2" nr="301"/>
            <line cb="0" ci="0" mb="2" mi="5" nr="312"/>
            <line cb="0" ci="0" mb="0" mi="5" nr="314"/>
            <line cb="0" ci="0" mb="2" mi="4" nr="318"/>
            <line cb="0" ci="0" mb="0" mi="4" nr="319"/>
            <line cb="0" ci="0" mb="0" mi="3" nr="321"/>
            <line cb="0" ci="0" mb="2" mi="5" nr="332"/>
            <line cb="0" ci="0" mb="0" mi="5" nr="334"/>
            <line cb="0" ci="0" mb="2" mi="4" nr="338"/>
            <line cb="0" ci="0" mb="0" mi="4" nr="339"/>
            <line cb="0" ci="0" mb="0" mi="3" nr="341"/>
            <line cb="0" ci="0" mb="0" mi="4" nr="351"/>
            <line cb="0" ci="0" mb="2" mi="3" nr="352"/>
            <line cb="0" ci="0" mb="0" mi="5" nr="353"/>
            <line cb="0" ci="0" mb="0" mi="2" nr="356"/>
            <line cb="0" ci="0" mb="0" mi="4" nr="366"/>
            <line cb="0" ci="0" mb="2" mi="3" nr="367"/>
            <line cb="0" ci="0" mb="0" mi="5" nr="368"/>
            <line cb="0" ci="0" mb="0" mi="2" nr="371"/>
            <line cb="0" ci="0" mb="0" mi="3" nr="380"/>
            <line cb="0" ci="0" mb="2" mi="2" nr="381"/>
            <line cb="0" ci="0" mb="0" mi="2" nr="382"/>
            <line cb="0" ci="0" mb="2" mi="9" nr="384"/>
            <line cb="0" ci="0" mb="0" mi="3" nr="393"/>
            <line cb="0" ci="0" mb="2" mi="2" nr="394"/>
            <line cb="0" ci="0" mb="0" mi="2" nr="395"/>
            <line cb="0" ci="0" mb="2" mi="9" nr="397"/>
            <line cb="0" ci="0" mb="2" mi="4" nr="406"/>
            <line cb="0" ci="0" mb="0" mi="3" nr="408"/>
            <line cb="0" ci="0" mb="0" mi="3" nr="411"/>
            <line cb="0" ci="0" mb="2" mi="4" nr="420"/>
            <line cb="0" ci="0" mb="0" mi="3" nr="422"/>
            <line cb="0" ci="0" mb="0" mi="3" nr="425"/>
            <line cb="0" ci="0" mb="0" mi="6" nr="434"/>
            <line cb="0" ci="0" mb="0" mi="7" nr="442"/>
            <line cb="0" ci="0" mb="0" mi="7" nr="448"/>
            <line cb="0" ci="0" mb="2" mi="5" nr="454"/>
            <line cb="0" ci="0" mb="0" mi="3" nr="455"/>
            <line cb="0" ci="0" mb="2" mi="13" nr="456"/>
            <line cb="0" ci="0" mb="0" mi="2" nr="458"/>
            <line cb="0" ci="0" mb="0" mi="2" nr="459"/>
            <line cb="0" ci="0" mb="2" mi="10" nr="460"/>
            <line cb="0" ci="0" mb="0" mi="8" nr="461"/>
            <line cb="0" ci="0" mb="0" mi="4" nr="462"/>
            <line cb="0" ci="0" mb="0" mi="12" nr="463"/>
            <line cb="0" ci="0" mb="0" mi="1" nr="464"/>
            <line cb="0" ci="0" mb="0" mi="3" nr="465"/>
            <line cb="0" ci="0" mb="2" mi="5" nr="466"/>
            <line cb="0" ci="0" mb="0" mi="4" nr="467"/>
            <line cb="0" ci="0" mb="2" mi="4" nr="468"/>
            <line cb="0" ci="0" mb="0" mi="11" nr="469"/>
            <line cb="0" ci="0" mb="0" mi="7" nr="471"/>
            <line cb="0" ci="0" mb="0" mi="4" nr="472"/>
            <line cb="0" ci="0" mb="0" mi="1" nr="475"/>
            <line cb="0" ci="0" mb="0" mi="4" nr="484"/>
            <line cb="0" ci="0" mb="0" mi="2" nr="486"/>
            <line cb="0" ci="0" mb="0" mi="2" nr="487"/>
            <line cb="0" ci="0" mb="0" mi="2" nr="488"/>
            <line cb="0" ci="0" mb="2" mi="10" nr="489"/>
            <line cb="0" ci="0" mb="2" mi="3" nr="491"/>
            <line cb="0" ci="0" mb="0" mi="4" nr="493"/>
            <line cb="0" ci="0" mb="2" mi="2" nr="496"/>
            <line cb="0" ci="0" mb="2" mi="6" nr="497"/>
            <line cb="0" ci="0" mb="2" mi="3" nr="500"/>
            <line cb="0" ci="0" mb="0" mi="3" nr="502"/>
            <line cb="0" ci="0" mb="0" mi="4" nr="504"/>
            <line cb="0" ci="0" mb="0" mi="6" nr="505"/>
            <line cb="0" ci="0" mb="2" mi="4" nr="506"/>
            <line cb="0" ci="0" mb="0" mi="10" nr="507"/>
            <line cb="0" ci="0" mb="0" mi="12" nr="509"/>
            <line cb="0" ci="0" mb="2" mi="6" nr="512"/>
            <line cb="0" ci="0" mb="0" mi="6" nr="515"/>
            <line cb="0" ci="0" mb="0" mi="6" nr="516"/>
            <line cb="0" ci="0" mb="2" mi="4" nr="517"/>
            <line cb="0" ci="0" mb="0" mi="12" nr="518"/>
            <line cb="0" ci="0" mb="0" mi="12" nr="520"/>
            <line cb="0" ci="0" mb="0" mi="4" nr="524"/>
            <line cb="0" ci="0" mb="0" mi="1" nr="525"/>
            <line cb="0" ci="0" mb="2" mi="3" nr="527"/>
            <line cb="0" ci="0" mb="0" mi="7" nr="530"/>
            <line cb="0" ci="0" mb="2" mi="2" nr="536"/>
            <line cb="0" ci="0" mb="0" mi="6" nr="538"/>
            <line cb="0" ci="0" mb="0" mi="4" nr="539"/>
            <line cb="0" ci="0" mb="2" mi="4" nr="540"/>
            <line cb="0" ci="0" mb="0" mi="10" nr="541"/>
            <line cb="0" ci="0" mb="0" mi="10" nr="543"/>
            <line cb="0" ci="0" mb="0" mi="4" nr="547"/>
            <line cb="0" ci="0" mb="0" mi="6" nr="548"/>
            <line cb="0" ci="0" mb="2" mi="4" nr="549"/>
            <line cb="0" ci="0" mb="0" mi="10" nr="550"/>
            <line cb="0" ci="0" mb="0" mi="10" nr="552"/>
            <line cb="0" ci="0" mb="0" mi="4" nr="568"/>
            <line cb="0" ci="0" mb="2" mi="10" nr="569"/>
            <line cb="0" ci="0" mb="0" mi="14" nr="570"/>
            <line cb="0" ci="0" mb="0" mi="1" nr="571"/>
            <line cb="0" ci="0" mb="0" mi="2" nr="572"/>
            <line cb="0" ci="0" mb="0" mi="5" nr="584"/>
            <line cb="0" ci="0" mb="0" mi="5" nr="601"/>
            <line cb="0" ci="0" mb="0" mi="4" nr="603"/>
            <line cb="0" ci="0" mb="0" mi="4" nr="604"/>
            <line cb="0" ci="0" mb="2" mi="3" nr="606"/>
            <line cb="0" ci="0" mb="2" mi="9" nr="608"/>
            <line cb="0" ci="0" mb="0" mi="13" nr="610"/>
            <line cb="0" ci="0" mb="0" mi="4" nr="614"/>
            <line cb="0" ci="0" mb="0" mi="2" nr="617"/>
            <line cb="0" ci="0" mb="0" mi="1" nr="619"/>
            <line cb="0" ci="0" mb="0" mi="3" nr="626"/>
            <line cb="0" ci="0" mb="4" mi="7" nr="627"/>
            <line cb="0" ci="0" mb="0" mi="6" nr="628"/>
            <line cb="0" ci="0" mb="2" mi="2" nr="631"/>
            <line cb="0" ci="0" mb="0" mi="3" nr="633"/>
            <line cb="0" ci="0" mb="0" mi="3" nr="634"/>
            <line cb="0" ci="0" mb="0" mi="1" nr="635"/>
            <line cb="0" ci="0" mb="0" mi="2" nr="639"/>
            <line cb="0" ci="0" mb="4" mi="7" nr="640"/>
            <line cb="0" ci="0" mb="0" mi="6" nr="641"/>
            <line cb="0" ci="0" mb="2" mi="2" nr="644"/>
            <line cb="0" ci="0" mb="0" mi="18" nr="647"/>
            <line cb="0" ci="0" mb="0" mi="4" nr="652"/>
            <line cb="0" ci="0" mb="0" mi="3" nr="657"/>
            <line cb="0" ci="0" mb="4" mi="7" nr="658"/>
            <line cb="0" ci="0" mb="0" mi="6" nr="659"/>
            <line cb="0" ci="0" mb="2" mi="2" nr="661"/>
            <line cb="0" ci="0" mb="0" mi="4" nr="663"/>
            <line cb="0" ci="0" mb="0" mi="20" nr="667"/>
            <line cb="0" ci="0" mb="0" mi="3" nr="672"/>
            <line cb="0" ci="0" mb="0" mi="1" nr="676"/>
            <line cb="0" ci="0" mb="2" mi="7" nr="680"/>
            <line cb="0" ci="0" mb="2" mi="3" nr="685"/>
            <line cb="0" ci="0" mb="0" mi="4" nr="686"/>
            <line cb="0" ci="0" mb="0" mi="3" nr="688"/>
            <line cb="0" ci="0" mb="0" mi="2" nr="689"/>
            <line cb="0" ci="0" mb="0" mi="2" nr="690"/>
            <line cb="0" ci="0" mb="0" mi="4" nr="695"/>
            <line cb="0" ci="0" mb="0" mi="5" nr="712"/>
            <line cb="0" ci="0" mb="0" mi="4" nr="723"/>
            <line cb="0" ci="0" mb="0" mi="4" nr="724"/>
            <line cb="0" ci="0" mb="0" mi="5" nr="726"/>
            <line cb="0" ci="0" mb="0" mi="6" nr="727"/>
            <line cb="0" ci="0" mb="2" mi="10" nr="729"/>
            <line cb="0" ci="0" mb="0" mi="9" nr="730"/>
            <line cb="0" ci="0" mb="0" mi="6" nr="731"/>
            <line cb="0" ci="0" mb="0" mi="6" nr="732"/>
            <line cb="0" ci="0" mb="2" mi="4" nr="733"/>
            <line cb="0" ci="0" mb="0" mi="7" nr="735"/>
            <line cb="0" ci="0" mb="2" mi="4" nr="736"/>
            <line cb="0" ci="0" mb="0" mi="4" nr="739"/>
            <line cb="0" ci="0" mb="0" mi="5" nr="740"/>
            <line cb="0" ci="0" mb="0" mi="5" nr="741"/>
            <line cb="0" ci="0" mb="2" mi="4" nr="742"/>
            <line cb="0" ci="0" mb="0" mi="4" nr="745"/>
            <line cb="0" ci="0" mb="0" mi="5" nr="746"/>
            <line cb="0" ci="0" mb="0" mi="5" nr="747"/>
            <line cb="0" ci="0" mb="0" mi="7" nr="748"/>
            <line cb="0" ci="0" mb="0" mi="1" nr="749"/>
            <line cb="0" ci="0" mb="0" mi="7" nr="751"/>
            <line cb="0" ci="0" mb="0" mi="1" nr="753"/>
            <line cb="0" ci="0" mb="0" mi="8" nr="755"/>
            <line cb="0" ci="0" mb="0" mi="7" nr="759"/>
            <line cb="0" ci="0" mb="2" mi="4" nr="760"/>
            <line cb="0" ci="0" mb="0" mi="4" nr="763"/>
            <line cb="0" ci="0" mb="0" mi="5" nr="764"/>
            <line cb="0" ci="0" mb="0" mi="5" nr="765"/>
            <line cb="0" ci="0" mb="2" mi="6" nr="766"/>
            <line cb="0" ci="0" mb="0" mi="6" nr="769"/>
            <line cb="0" ci="0" mb="0" mi="5" nr="770"/>
            <line cb="0" ci="0" mb="0" mi="5" nr="771"/>
            <line cb="0" ci="0" mb="0" mi="7" nr="772"/>
            <line cb="0" ci="0" mb="0" mi="1" nr="773"/>
            <line cb="0" ci="0" mb="0" mi="7" nr="775"/>
            <line cb="0" ci="0" mb="0" mi="1" nr="777"/>
            <line cb="0" ci="0" mb="0" mi="7" nr="779"/>
            <line cb="0" ci="0" mb="0" mi="1" nr="782"/>
            <line cb="0" ci="0" mb="0" mi="11" nr="784"/>
            <line cb="0" ci="0" mb="2" mi="15" nr="795"/>
            <line cb="0" ci="0" mb="0" mi="7" nr="796"/>
            <line cb="0" ci="0" mb="2" mi="3" nr="797"/>
            <line cb="0" ci="0" mb="0" mi="4" nr="799"/>
            <line cb="0" ci="0" mb="0" mi="4" nr="802"/>
            <line cb="0" ci="0" mb="0" mi="3" nr="803"/>
            <line cb="0" ci="0" mb="0" mi="4" nr="804"/>
            <line cb="0" ci="0" mb="0" mi="4" nr="805"/>
            <line cb="0" ci="0" mb="0" mi="1" nr="807"/>
            <line cb="0" ci="0" mb="2" mi="3" nr="819"/>
            <line cb="0" ci="0" mb="0" mi="2" nr="820"/>
            <line cb="0" ci="0" mb="2" mi="8" nr="824"/>
            <line cb="0" ci="0" mb="0" mi="7" nr="825"/>
            <line cb="0" ci="0" mb="0" mi="6" nr="826"/>
            <line cb="0" ci="0" mb="0" mi="8" nr="827"/>
            <line cb="0" ci="0" mb="2" mi="8" nr="828"/>
            <line cb="0" ci="0" mb="2" mi="2" nr="830"/>
            <line cb="0" ci="0" mb="0" mi="4" nr="832"/>
            <line cb="0" ci="0" mb="0" mi="4" nr="833"/>
            <line cb="0" ci="0" mb="0" mi="5" nr="834"/>
            <line cb="0" ci="0" mb="0" mi="9" nr="838"/>
            <line cb="0" ci="0" mb="0" mi="6" nr="839"/>
            <line cb="0" ci="0" mb="2" mi="3" nr="840"/>
            <line cb="0" ci="0" mb="2" mi="6" nr="842"/>
            <line cb="0" ci="0" mb="0" mi="10" nr="844"/>
            <line cb="0" ci="0" mb="0" mi="2" nr="847"/>
            <line cb="0" ci="0" mb="0" mi="11" nr="853"/>
            <line cb="0" ci="0" mb="0" mi="5" nr="860"/>
            <line cb="0" ci="0" mb="2" mi="10" nr="861"/>
            <line cb="0" ci="0" mb="0" mi="9" nr="862"/>
            <line cb="0" ci="0" mb="0" mi="11" nr="863"/>
            <line cb="0" ci="0" mb="2" mi="3" nr="866"/>
            <line cb="0" ci="0" mb="0" mi="2" nr="868"/>
            <line cb="0" ci="0" mb="0" mi="7" nr="871"/>
            <line cb="0" ci="0" mb="0" mi="2" nr="892"/>
            <line cb="0" ci="0" mb="0" mi="3" nr="893"/>
            <line cb="0" ci="0" mb="0" mi="3" nr="894"/>
            <line cb="0" ci="0" mb="0" mi="1" nr="895"/>
            <line cb="0" ci="0" mb="0" mi="3" nr="901"/>
            <line cb="0" ci="0" mb="0" mi="3" nr="908"/>
            <line cb="0" ci="0" mb="2" mi="3" nr="920"/>
            <line cb="0" ci="0" mb="2" mi="3" nr="921"/>
            <line cb="0" ci="0" mb="0" mi="2" nr="922"/>
            <line cb="0" ci="0" mb="0" mi="2" nr="924"/>
            <line cb="0" ci="0" mb="2" mi="3" nr="926"/>
            <line cb="0" ci="0" mb="0" mi="2" nr="927"/>
            <line cb="0" ci="0" mb="0" mi="2" nr="929"/>
            <line cb="0" ci="0" mb="0" mi="5" nr="950"/>
            <line cb="0" ci="0" mb="0" mi="1" nr="951"/>
            <counter covered="0" missed="1400" type="INSTRUCTION"/>
            <counter covered="0" missed="158" type="BRANCH"/>
            <counter covered="0" missed="281" type="LINE"/>
            <counter covered="0" missed="119" type="COMPLEXITY"/>
            <counter covered="0" missed="40" type="METHOD"/>
            <counter covered="0" missed="4" type="CLASS"/>
        </sourcefile>
        <sourcefile name="S1Point.java">
            <line cb="0" ci="0" mb="0" mi="7" nr="33"/>
            <line cb="0" ci="0" mb="0" mi="12" nr="51"/>
            <line cb="0" ci="0" mb="0" mi="1" nr="53"/>
            <line cb="0" ci="0" mb="0" mi="2" nr="59"/>
            <line cb="0" ci="0" mb="0" mi="3" nr="60"/>
            <line cb="0" ci="0" mb="0" mi="3" nr="61"/>
            <line cb="0" ci="0" mb="0" mi="1" nr="62"/>
            <line cb="0" ci="0" mb="0" mi="3" nr="69"/>
            <line cb="0" ci="0" mb="0" mi="3" nr="76"/>
            <line cb="0" ci="0" mb="0" mi="2" nr="81"/>
            <line cb="0" ci="0" mb="0" mi="4" nr="86"/>
            <line cb="0" ci="0" mb="0" mi="5" nr="91"/>
            <line cb="0" ci="0" mb="0" mi="6" nr="100"/>
            <line cb="0" ci="0" mb="2" mi="3" nr="125"/>
            <line cb="0" ci="0" mb="0" mi="2" nr="126"/>
            <line cb="0" ci="0" mb="2" mi="3" nr="129"/>
            <line cb="0" ci="0" mb="0" mi="3" nr="130"/>
            <line cb="0" ci="0" mb="2" mi="3" nr="131"/>
            <line cb="0" ci="0" mb="0" mi="3" nr="132"/>
            <line cb="0" ci="0" mb="2" mi="10" nr="135"/>
            <line cb="0" ci="0" mb="0" mi="2" nr="138"/>
            <line cb="0" ci="0" mb="2" mi="3" nr="151"/>
            <line cb="0" ci="0" mb="0" mi="2" nr="152"/>
            <line cb="0" ci="0" mb="0" mi="6" nr="154"/>
            <counter covered="0" missed="92" type="INSTRUCTION"/>
            <counter covered="0" missed="10" type="BRANCH"/>
            <counter covered="0" missed="24" type="LINE"/>
            <counter covered="0" missed="16" type="COMPLEXITY"/>
            <counter covered="0" missed="11" type="METHOD"/>
            <counter covered="0" missed="1" type="CLASS"/>
        </sourcefile>
        <sourcefile name="Sphere1D.java">
            <line cb="0" ci="0" mb="0" mi="2" nr="50"/>
            <line cb="0" ci="0" mb="0" mi="2" nr="55"/>
            <line cb="0" ci="0" mb="0" mi="4" nr="67"/>
            <line cb="0" ci="0" mb="0" mi="6" nr="76"/>
            <line cb="0" ci="0" mb="0" mi="2" nr="85"/>
            <line cb="0" ci="0" mb="0" mi="10" nr="101"/>
            <line cb="0" ci="0" mb="0" mi="1" nr="102"/>
            <counter covered="0" missed="27" type="INSTRUCTION"/>
            <counter covered="0" missed="7" type="LINE"/>
            <counter covered="0" missed="6" type="COMPLEXITY"/>
            <counter covered="0" missed="6" type="METHOD"/>
            <counter covered="0" missed="3" type="CLASS"/>
        </sourcefile>
        <counter covered="0" missed="1771" type="INSTRUCTION"/>
        <counter covered="0" missed="192" type="BRANCH"/>
        <counter covered="0" missed="358" type="LINE"/>
        <counter covered="0" missed="176" type="COMPLEXITY"/>
        <counter covered="0" missed="80" type="METHOD"/>
        <counter covered="0" missed="11" type="CLASS"/>
    </package></report>